niceback/__init__.py
niceback/html.py
niceback/inspector.py
niceback/logging.py
niceback/notebook.py
niceback/style.css
niceback/trace.py
niceback-0.4.2.dist-info/METADATA
niceback-0.4.2.dist-info/WHEEL
niceback-0.4.2.dist-info/top_level.txt
niceback-0.4.2.dist-info/RECORD
