Metadata-Version: 2.1
Name: niceback
Version: 0.4.2
Summary: Human-readable tracebacks in Jupyter notebooks
Home-page: https://github.com/Tronic/niceback
Author: L. Kärkkäinen
Author-email: tronic@noreply.users.github.com
License: UNKNOWN
Platform: UNKNOWN
Classifier: Programming Language :: Python :: 3
Classifier: License :: OSI Approved :: MIT License
Classifier: License :: Public Domain
Classifier: Operating System :: OS Independent
Requires-Dist: html5tagger (>=1.0.0)
